nextcordSuperUtils/__init__.py
nextcordSuperUtils/antispam.py
nextcordSuperUtils/ban.py
nextcordSuperUtils/base.py
nextcordSuperUtils/birthday.py
nextcordSuperUtils/client.py
nextcordSuperUtils/commandhinter.py
nextcordSuperUtils/convertors.py
nextcordSuperUtils/database.py
nextcordSuperUtils/economy.py
nextcordSuperUtils/fivem.py
nextcordSuperUtils/imaging.py
nextcordSuperUtils/infractions.py
nextcordSuperUtils/invitetracker.py
nextcordSuperUtils/kick.py
nextcordSuperUtils/leveling.py
nextcordSuperUtils/messagefilter.py
nextcordSuperUtils/modmail.py
nextcordSuperUtils/mute.py
nextcordSuperUtils/paginator.py
nextcordSuperUtils/prefix.py
nextcordSuperUtils/punishments.py
nextcordSuperUtils/reactionroles.py
nextcordSuperUtils/spotify.py
nextcordSuperUtils/template.py
nextcordSuperUtils/twitch.py
nextcordSuperUtils/youtube.py
nextcordSuperUtils-0.3.1.dist-info/LICENSE
nextcordSuperUtils-0.3.1.dist-info/METADATA
nextcordSuperUtils-0.3.1.dist-info/WHEEL
nextcordSuperUtils-0.3.1.dist-info/top_level.txt
nextcordSuperUtils-0.3.1.dist-info/RECORD
