Metadata-Version: 2.1
Name: nextcordSuperUtils
Version: 0.3.1
Summary: Discord Bot Development made easy!
Home-page: https://github.com/Cu3t0m/nextcord-super-utils
Author: Custom
License: MIT
Download-URL: https://github.com/Cu3t0m/nextcordsuperutils/archive/refs/tags/v0.3.0.tar.gz
Keywords: nextcord,easy,nextcord.py,music,download,links,images,videos,audio,bot,paginator,economy,reaction,reaction roles,database,database manager
Platform: UNKNOWN
Classifier: Development Status :: 4 - Beta
Classifier: Intended Audience :: Developers
Classifier: Topic :: Software Development :: Build Tools
Classifier: License :: OSI Approved :: MIT License
Classifier: Programming Language :: Python :: 3
Classifier: Programming Language :: Python :: 3.4
Classifier: Programming Language :: Python :: 3.5
Classifier: Programming Language :: Python :: 3.6
Requires-Dist: nextcord.py
Requires-Dist: Pillow
Requires-Dist: requests
Requires-Dist: spotipy
Requires-Dist: aiosqlite
Requires-Dist: motor
Requires-Dist: aiopg
Requires-Dist: aiomysql
Requires-Dist: nextcord-components
Requires-Dist: pytz
Requires-Dist: wavelink
Requires-Dist: youtube-dl
